conshex/__init__.py
conshex/core.py
conshex/date.py
conshex/debug.py
conshex/errors.py
conshex/expr.py
conshex/helpers.py
conshex/lazy.py
conshex/numbers.py
conshex/string.py
conshex/version.py
conshex/lib/__init__.py
conshex/lib/binary.py
conshex/lib/bitstream.py
conshex/lib/containers.py
conshex/lib/hex.py
conshex/lib/py3compat.py
conshex-0.2.3.dist-info/licenses/LICENSE
conshex-0.2.3.dist-info/METADATA
conshex-0.2.3.dist-info/WHEEL
conshex-0.2.3.dist-info/top_level.txt
conshex-0.2.3.dist-info/RECORD
