Metadata-Version: 2.4
Name: conshex
Version: 0.2.3
Summary: A powerful declarative symmetric parser/builder for binary data with XML de- and encoding
Home-page: http://conshex.readthedocs.org
Author: Tim Blume
Author-email: conshex@3nd.io
License: MIT
Project-URL: Source, https://github.com/ev1313/conshex
Project-URL: Documentation, https://conshex.readthedocs.io/en/latest/
Project-URL: Issues, https://github.com/ev1313/conshex/issues
Keywords: conshex,construct,declarative,data structure,struct,binary,symmetric,parser,builder,parsing,building,pack,unpack,packer,unpacker,xml
Platform: POSIX
Platform: Windows
Classifier: License :: OSI Approved :: MIT License
Classifier: Intended Audience :: Developers
Classifier: Topic :: Software Development :: Libraries :: Python Modules
Classifier: Topic :: Software Development :: Build Tools
Classifier: Programming Language :: Python :: 3
Classifier: Programming Language :: Python :: 3.13
Classifier: Programming Language :: Python :: Implementation :: PyPy
Requires-Python: >=3.10
License-File: LICENSE
Provides-Extra: extras
Requires-Dist: enum34; extra == "extras"
Requires-Dist: numpy; extra == "extras"
Requires-Dist: arrow; extra == "extras"
Requires-Dist: ruamel.yaml; extra == "extras"
Requires-Dist: lz4; extra == "extras"
Requires-Dist: cryptography; extra == "extras"
Dynamic: author
Dynamic: author-email
Dynamic: classifier
Dynamic: description
Dynamic: home-page
Dynamic: keywords
Dynamic: license
Dynamic: license-file
Dynamic: platform
Dynamic: project-url
Dynamic: provides-extra
Dynamic: requires-python
Dynamic: summary
